document_sorter/__init__.py
document_sorter/main.py
document_sorter-0.1.0.dist-info/METADATA
document_sorter-0.1.0.dist-info/WHEEL
document_sorter-0.1.0.dist-info/entry_points.txt
document_sorter-0.1.0.dist-info/top_level.txt
document_sorter-0.1.0.dist-info/RECORD
