Metadata-Version: 2.1
Name: document-sorter
Version: 0.1.0
Summary: A package to automatically sort documents into folders based on content similarity
Home-page: https://github.com/jazmiahenry/document_sorter
Author: Jazmia
Author-email: jazmia.henry@google.com
License: UNKNOWN
Platform: UNKNOWN
Classifier: Development Status :: 3 - Alpha
Classifier: Intended Audience :: Developers
Classifier: License :: OSI Approved :: MIT License
Classifier: Operating System :: OS Independent
Classifier: Programming Language :: Python :: 3
Classifier: Programming Language :: Python :: 3.6
Classifier: Programming Language :: Python :: 3.7
Classifier: Programming Language :: Python :: 3.8
Classifier: Programming Language :: Python :: 3.9
Requires-Python: >=3.6
Requires-Dist: PyPDF2 (==2.10.5)
Requires-Dist: openpyxl (==3.1.1)
Requires-Dist: pandas (==1.4.4)
Requires-Dist: python-docx (==0.8.11)
Requires-Dist: scikit-learn (==1.0.2)
Requires-Dist: tqdm (==4.64.1)
Requires-Dist: numpy (==1.21.5)
Requires-Dist: scipy (==1.7.3)
Requires-Dist: packaging (==21.3)
